py2code/__init__.py
py2code/codegen.py
py2code/generator.py
py2code-0.2.3.dist-info/licenses/LICENSE
py2code-0.2.3.dist-info/METADATA
py2code-0.2.3.dist-info/WHEEL
py2code-0.2.3.dist-info/top_level.txt
py2code-0.2.3.dist-info/RECORD
