Metadata-Version: 2.4
Name: py2code
Version: 0.2.3
Summary: A Python package for generating source code in C, C++, C#, and Java from python code.
Home-page: https://github.com/ojari/codegen
Author: Jari Ojanen
Classifier: Programming Language :: Python :: 3
Classifier: Intended Audience :: Developers
Classifier: Topic :: Software Development
Classifier: Topic :: Software Development :: Code Generators
Requires-Python: >=3.9
License-File: LICENSE
Dynamic: author
Dynamic: classifier
Dynamic: description
Dynamic: description-content-type
Dynamic: home-page
Dynamic: license-file
Dynamic: requires-python
Dynamic: summary
